{
    "$schema": "https://json.schemastore.org/tsconfig",
    "display": "Base",
    "compilerOptions": {
        "esModuleInterop": true,
        "declaration": true,
        "declarationMap": true,
        "incremental": false,
        "isolatedModules": true,
        "allowUnreachableCode": true,
        "moduleDetection": "force",
        "moduleResolution": "node",
        "noUncheckedIndexedAccess": true,
        "resolveJsonModule": true,
        "skipLibCheck": true,
        "strict": true,
        "forceConsistentCasingInFileNames": true
    },
    "exclude": ["node_modules", "dist"]
}
